diabetes_analysis_malk_alobiedy.py
diabetes_analysis_malk_alobiedy-0.1.1.dist-info/METADATA
diabetes_analysis_malk_alobiedy-0.1.1.dist-info/WHEEL
diabetes_analysis_malk_alobiedy-0.1.1.dist-info/top_level.txt
diabetes_analysis_malk_alobiedy-0.1.1.dist-info/RECORD
